cognee_community_pipeline_codify/__init__.py
cognee_community_pipeline_codify/code_graph_pipeline.py
cognee_community_pipeline_codify-0.1.0.dist-info/METADATA
cognee_community_pipeline_codify-0.1.0.dist-info/WHEEL
cognee_community_pipeline_codify-0.1.0.dist-info/RECORD
